cmislib/__init__.py
cmislib/atompub_binding.py
cmislib/browser_binding.py
cmislib/cmis_services.py
cmislib/domain.py
cmislib/exceptions.py
cmislib/messages.py
cmislib/model.py
cmislib/net.py
cmislib/util.py
cmislib/atompub/__init__.py
cmislib/atompub/binding.py
cmislib/browser/__init__.py
cmislib/browser/binding.py
cmislib_maykin-0.7.4.dist-info/LICENSE.txt
cmislib_maykin-0.7.4.dist-info/METADATA
cmislib_maykin-0.7.4.dist-info/NOTICE.txt
cmislib_maykin-0.7.4.dist-info/WHEEL
cmislib_maykin-0.7.4.dist-info/top_level.txt
cmislib_maykin-0.7.4.dist-info/RECORD
