Metadata-Version: 2.1
Name: cmislib-maykin
Version: 0.7.4
Summary: Apache Chemistry CMIS client library for Python
Home-page: http://chemistry.apache.org/
Author: Apache Chemistry Project
Author-email: dev@chemistry.apache.org
License: Apache License (2.0)
Platform: UNKNOWN
Classifier: Development Status :: 4 - Beta
Classifier: Intended Audience :: Developers
Classifier: License :: OSI Approved :: Apache Software License
Classifier: Operating System :: OS Independent
Classifier: Programming Language :: Python
Classifier: Topic :: Software Development :: Libraries
Requires-Dist: iso8601
Requires-Dist: httplib2
Requires-Dist: six
